{

  "reference_tracks": [
    {
        "reference_track_id" : "00001",
        "turning_points": [
          {
            "lat": 40.2,
            "lon": 12.3,
            "h": 0
          },
          {
            "lat": 40.5,
            "lon": 12.3,
            "h": 200
          },
          {
            "lat": 40.5,
            "lon": 12.8,
            "h": 200
          },
          {
            "lat": 40.9,
            "lon": 13.0,
            "h": 300
          }
        ]
    },

   {
        "reference_track_id" : "00002",
        "turning_points": [
          {
            "lat": 40.2,
            "lon": 12.3,
            "h": 0
          },
          {
            "lat": 40.5,
            "lon": 12.3,
            "h": 200
          },
          {
            "lat": 40.5,
            "lon": 12.8,
            "h": 200
          },
          {
            "lat": 40.9,
            "lon": 13.0,
            "h": 300
          }
        ]
    },

   {
        "reference_track_id" : "00003",
        "turning_points": [
          {
            "lat": 40.2,
            "lon": 12.3,
            "h": 0
          },
          {
            "lat": 40.5,
            "lon": 12.3,
            "h": 200
          },
          {
            "lat": 40.5,
            "lon": 12.8,
            "h": 200
          },
          {
            "lat": 40.9,
            "lon": 13.0,
            "h": 300
          }
        ]
    },
    {
        "reference_track_id" : "00004",
        "turning_points": [
          {
            "lat": 40.2,
            "lon": 12.3,
            "h": 0
          },
          {
            "lat": 40.5,
            "lon": 12.3,
            "h": 200
          },
          {
            "lat": 40.5,
            "lon": 12.8,
            "h": 200
          },
          {
            "lat": 40.9,
            "lon": 13.0,
            "h": 300
          }
        ]
    },
    {
        "reference_track_id" : "00005",
        "turning_points": [
          {
            "lat": 40.2,
            "lon": 12.3,
            "h": 0
          },
          {
            "lat": 40.5,
            "lon": 12.3,
            "h": 200
          },
          {
            "lat": 40.5,
            "lon": 12.8,
            "h": 200
          },
          {
            "lat": 40.9,
            "lon": 13.0,
            "h": 300
          }
        ]
    },
    {
        "reference_track_id" : "00006",
        "turning_points": [
          {
            "lat": 40.2,
            "lon": 12.3,
            "h": 0
          },
          {
            "lat": 40.5,
            "lon": 12.3,
            "h": 200
          },
          {
            "lat": 40.5,
            "lon": 12.8,
            "h": 200
          },
          {
            "lat": 40.9,
            "lon": 13.0,
            "h": 300
          }
        ]
    }

  ]
}